qgis_mcp/qgis_mcp_server.py
qgis_mcp/qgis_socket_client.py
iflow_mcp_qgis_mcp-0.1.0.dist-info/METADATA
iflow_mcp_qgis_mcp-0.1.0.dist-info/WHEEL
iflow_mcp_qgis_mcp-0.1.0.dist-info/entry_points.txt
iflow_mcp_qgis_mcp-0.1.0.dist-info/top_level.txt
iflow_mcp_qgis_mcp-0.1.0.dist-info/RECORD
