Metadata-Version: 2.4
Name: iflow-mcp_qgis-mcp
Version: 0.1.0
Summary: Add your description here
Requires-Python: >=3.12
Requires-Dist: mcp[cli]>=1.3.0
